{
  "scenario": 3,
  "scheme": "ub_rg",
  "mode": "roundtrip",
  "batch": 64,
  "zipf_s": 0.700000,
  "topk": 8,
  "ep_size": 1024,
  "seed": 17,
  "tau_g_ns": 143.360000,
  "grain_bytes": 7168,
  "total_tokens": 1048576,
  "max_egress_load": 2436,
  "konig_us": 691.138560,
  "rtt_us": 1.100000,
  "barrier_us": 2.400000,
  "cct_us": 702.357811,
  "step_us": 704.757811,
  "throughput_GBs": 10664.930068,
  "latency_all": {
    "count": 1048576,
    "mean_us": 24.305569,
    "p50_us": 5.264538,
    "p99_us": 89.166251,
    "min_us": 2.043500,
    "max_us": 351.182491
  },
  "latency_hot": {
    "count": 456552,
    "mean_us": 47.354062,
    "p50_us": 20.465002,
    "p99_us": 102.983054,
    "min_us": 2.043500,
    "max_us": 351.182491
  },
  "latency_cold": {
    "count": 223232,
    "mean_us": 5.257293,
    "p50_us": 4.775266,
    "p99_us": 8.392347,
    "min_us": 2.043577,
    "max_us": 16.012367
  },
  "dispatch_cct_us": 351.182491,
  "combine_cct_us": 351.175320,
  "roundtrip_step_us": 704.757811
}
