{
  "scenario": 1,
  "scheme": "packet_spray",
  "mode": "roundtrip",
  "batch": 64,
  "zipf_s": 0.000000,
  "topk": 8,
  "ep_size": 32,
  "seed": 3,
  "start_skew_us": 4.000000,
  "tau_g_ns": 143.360000,
  "grain_bytes": 7168,
  "total_tokens": 32768,
  "max_egress_load": 91,
  "konig_us": 23.367680,
  "rtt_us": 0.000000,
  "barrier_us": 4.000000,
  "cct_us": 66.833229,
  "step_us": 93.255104,
  "gemv_us": 22.421875,
  "e2e_us": 89.255104,
  "throughput_GBs": 2518.693508,
  "latency_all": {
    "count": 32768,
    "mean_us": 24.623855,
    "p50_us": 24.555587,
    "p99_us": 35.292081,
    "min_us": 7.041069,
    "max_us": 37.299121
  },
  "latency_hot": {
    "count": 3178,
    "mean_us": 21.993050,
    "p50_us": 22.160097,
    "p99_us": 28.387627,
    "min_us": 8.386668,
    "max_us": 29.390748
  },
  "latency_cold": {
    "count": 16294,
    "mean_us": 25.876286,
    "p50_us": 26.260401,
    "p99_us": 35.865521,
    "min_us": 8.386668,
    "max_us": 37.299121
  },
  "dispatch_cct_us": 29.534108,
  "combine_cct_us": 37.299121,
  "roundtrip_step_us": 70.833229,
  "e2e_step_us": 93.255104
}
