{
  "scenario": 4,
  "scheme": "packet_spray",
  "mode": "roundtrip",
  "batch": 256,
  "zipf_s": 0.700000,
  "topk": 8,
  "ep_size": 256,
  "seed": 87,
  "start_skew_us": 4.000000,
  "tau_g_ns": 143.360000,
  "grain_bytes": 7168,
  "total_tokens": 1048576,
  "max_egress_load": 4075,
  "konig_us": 1103.728640,
  "rtt_us": 0.000000,
  "barrier_us": 6.000000,
  "cct_us": 1179.882811,
  "step_us": 2318.226561,
  "gemv_us": 1132.343750,
  "e2e_us": 2312.226561,
  "throughput_GBs": 3242.216656,
  "latency_all": {
    "count": 1048576,
    "mean_us": 180.553465,
    "p50_us": 45.545142,
    "p99_us": 228.325933,
    "min_us": 0.214316,
    "max_us": 614.026186
  },
  "latency_hot": {
    "count": 404878,
    "mean_us": 203.480206,
    "p50_us": 105.796425,
    "p99_us": 503.290443,
    "min_us": 0.214316,
    "max_us": 590.515146
  },
  "latency_cold": {
    "count": 242748,
    "mean_us": 166.246622,
    "p50_us": 50.272813,
    "p99_us": 538.618826,
    "min_us": 0.529031,
    "max_us": 614.026186
  },
  "dispatch_cct_us": 565.856625,
  "combine_cct_us": 614.026186,
  "roundtrip_step_us": 1185.882811,
  "e2e_step_us": 2318.226561
}
