{
  "scenario": 4,
  "scheme": "ub_rg",
  "mode": "roundtrip",
  "batch": 512,
  "zipf_s": 0.700000,
  "topk": 8,
  "ep_size": 512,
  "seed": 28,
  "start_skew_us": 4.000000,
  "tau_g_ns": 143.360000,
  "grain_bytes": 7168,
  "total_tokens": 4194304,
  "max_egress_load": 12993,
  "konig_us": 3545.006080,
  "rtt_us": 0.800000,
  "barrier_us": 1.600000,
  "cct_us": 3764.563595,
  "step_us": 7433.351095,
  "gemv_us": 3667.187500,
  "e2e_us": 7431.751095,
  "throughput_GBs": 4044.578372,
  "latency_all": {
    "count": 4194304,
    "mean_us": 148.948026,
    "p50_us": 32.729183,
    "p99_us": 1112.152015,
    "min_us": 1.398291,
    "max_us": 1883.400339
  },
  "latency_hot": {
    "count": 1743348,
    "mean_us": 294.085983,
    "p50_us": 63.066495,
    "p99_us": 1111.841455,
    "min_us": 3.221974,
    "max_us": 1883.400339
  },
  "latency_cold": {
    "count": 924656,
    "mean_us": 32.884042,
    "p50_us": 26.248784,
    "p99_us": 51.986472,
    "min_us": 1.398291,
    "max_us": 98.810107
  },
  "dispatch_cct_us": 1881.163256,
  "combine_cct_us": 1883.400339,
  "roundtrip_step_us": 3766.163595,
  "e2e_step_us": 7433.351095
}
