{
  "scenario": 1,
  "scheme": "packet_spray",
  "mode": "roundtrip",
  "batch": 256,
  "zipf_s": 0.900000,
  "topk": 8,
  "ep_size": 32,
  "seed": 8,
  "tau_g_ns": 143.360000,
  "grain_bytes": 7168,
  "total_tokens": 131072,
  "max_egress_load": 947,
  "konig_us": 267.796480,
  "rtt_us": 0.000000,
  "barrier_us": 4.000000,
  "cct_us": 332.951840,
  "step_us": 336.951840,
  "throughput_GBs": 2788.303800,
  "latency_all": {
    "count": 131072,
    "mean_us": 72.265453,
    "p50_us": 62.898320,
    "p99_us": 155.652240,
    "min_us": 0.536720,
    "max_us": 167.551120
  },
  "latency_hot": {
    "count": 36458,
    "mean_us": 78.498242,
    "p50_us": 78.811280,
    "p99_us": 156.942480,
    "min_us": 0.536720,
    "max_us": 167.551120
  },
  "latency_cold": {
    "count": 33446,
    "mean_us": 69.635297,
    "p50_us": 50.712720,
    "p99_us": 159.953040,
    "min_us": 0.536720,
    "max_us": 165.400720
  },
  "dispatch_cct_us": 167.551120,
  "combine_cct_us": 165.400720,
  "roundtrip_step_us": 336.951840
}
