{
  "scenario": 1,
  "scheme": "packet_spray",
  "mode": "roundtrip",
  "batch": 64,
  "zipf_s": 0.700000,
  "topk": 8,
  "ep_size": 128,
  "seed": 11,
  "start_skew_us": 4.000000,
  "tau_g_ns": 143.360000,
  "grain_bytes": 7168,
  "total_tokens": 131072,
  "max_egress_load": 600,
  "konig_us": 167.301120,
  "rtt_us": 0.000000,
  "barrier_us": 4.000000,
  "cct_us": 190.035921,
  "step_us": 371.067171,
  "gemv_us": 177.031250,
  "e2e_us": 367.067171,
  "throughput_GBs": 2531.951542,
  "latency_all": {
    "count": 131072,
    "mean_us": 34.299979,
    "p50_us": 24.516128,
    "p99_us": 88.220513,
    "min_us": 0.960270,
    "max_us": 96.654449
  },
  "latency_hot": {
    "count": 45154,
    "mean_us": 38.485776,
    "p50_us": 33.185757,
    "p99_us": 85.640033,
    "min_us": 1.677070,
    "max_us": 96.654449
  },
  "latency_cold": {
    "count": 32146,
    "mean_us": 32.064685,
    "p50_us": 16.110433,
    "p99_us": 90.370913,
    "min_us": 1.103630,
    "max_us": 93.381473
  },
  "dispatch_cct_us": 96.654449,
  "combine_cct_us": 93.381473,
  "roundtrip_step_us": 194.035921,
  "e2e_step_us": 371.067171
}
