{
  "scenario": 4,
  "scheme": "ub_rg",
  "mode": "roundtrip",
  "batch": 512,
  "zipf_s": 0.000000,
  "topk": 8,
  "ep_size": 128,
  "seed": 76,
  "start_skew_us": 4.000000,
  "tau_g_ns": 143.360000,
  "grain_bytes": 7168,
  "total_tokens": 1048576,
  "max_egress_load": 632,
  "konig_us": 179.916800,
  "rtt_us": 0.800000,
  "barrier_us": 1.600000,
  "cct_us": 215.394995,
  "step_us": 381.916870,
  "gemv_us": 164.921875,
  "e2e_us": 380.316870,
  "throughput_GBs": 19680.180041,
  "latency_all": {
    "count": 1048576,
    "mean_us": 50.184160,
    "p50_us": 30.932684,
    "p99_us": 84.976845,
    "min_us": 1.054683,
    "max_us": 108.489954
  },
  "latency_hot": {
    "count": 98498,
    "mean_us": 49.815834,
    "p50_us": 49.613244,
    "p99_us": 91.508936,
    "min_us": 2.384041,
    "max_us": 106.531144
  },
  "latency_cold": {
    "count": 523878,
    "mean_us": 50.267590,
    "p50_us": 44.093863,
    "p99_us": 79.311779,
    "min_us": 1.343413,
    "max_us": 108.092567
  },
  "dispatch_cct_us": 108.489954,
  "combine_cct_us": 106.905041,
  "roundtrip_step_us": 216.994995,
  "e2e_step_us": 381.916870
}
