{
  "scenario": 1,
  "scheme": "islip",
  "mode": "roundtrip",
  "batch": 16,
  "zipf_s": 0.700000,
  "topk": 8,
  "ep_size": 128,
  "seed": 53,
  "start_skew_us": 4.000000,
  "tau_g_ns": 143.360000,
  "grain_bytes": 7168,
  "total_tokens": 32768,
  "max_egress_load": 149,
  "konig_us": 40.570880,
  "rtt_us": 0.600000,
  "barrier_us": 0.800000,
  "cct_us": 48.510305,
  "step_us": 91.068118,
  "gemv_us": 41.757812,
  "e2e_us": 90.268118,
  "throughput_GBs": 2579.179517,
  "latency_all": {
    "count": 32768,
    "mean_us": 5.555924,
    "p50_us": 4.797737,
    "p99_us": 18.514683,
    "min_us": 1.189913,
    "max_us": 25.983169
  },
  "latency_hot": {
    "count": 10908,
    "mean_us": 8.228149,
    "p50_us": 7.376711,
    "p99_us": 20.916451,
    "min_us": 1.224119,
    "max_us": 25.983169
  },
  "latency_cold": {
    "count": 8150,
    "mean_us": 3.696100,
    "p50_us": 3.584315,
    "p99_us": 6.488498,
    "min_us": 1.216574,
    "max_us": 7.271878
  },
  "dispatch_cct_us": 25.983169,
  "combine_cct_us": 22.527136,
  "roundtrip_step_us": 49.310305,
  "e2e_step_us": 91.068118
}
