{
  "scenario": 4,
  "scheme": "packet_spray",
  "mode": "roundtrip",
  "batch": 256,
  "zipf_s": 0.300000,
  "topk": 8,
  "ep_size": 256,
  "seed": 42,
  "start_skew_us": 4.000000,
  "tau_g_ns": 143.360000,
  "grain_bytes": 7168,
  "total_tokens": 1048576,
  "max_egress_load": 1027,
  "konig_us": 282.419200,
  "rtt_us": 0.000000,
  "barrier_us": 6.000000,
  "cct_us": 363.698306,
  "step_us": 664.190493,
  "gemv_us": 294.492188,
  "e2e_us": 658.190493,
  "throughput_GBs": 11316.320909,
  "latency_all": {
    "count": 1048576,
    "mean_us": 71.318024,
    "p50_us": 44.546746,
    "p99_us": 84.338104,
    "min_us": 0.459298,
    "max_us": 187.742770
  },
  "latency_hot": {
    "count": 195026,
    "mean_us": 72.516284,
    "p50_us": 70.879841,
    "p99_us": 147.290721,
    "min_us": 0.725540,
    "max_us": 175.955536
  },
  "latency_cold": {
    "count": 409356,
    "mean_us": 73.382282,
    "p50_us": 50.461976,
    "p99_us": 68.547974,
    "min_us": 0.499215,
    "max_us": 187.742770
  },
  "dispatch_cct_us": 175.955536,
  "combine_cct_us": 187.742770,
  "roundtrip_step_us": 369.698306,
  "e2e_step_us": 664.190493
}
