{
  "scenario": 4,
  "scheme": "ub_rg_pop",
  "mode": "roundtrip",
  "batch": 64,
  "zipf_s": 0.000000,
  "topk": 8,
  "ep_size": 128,
  "seed": 88,
  "start_skew_us": 4.000000,
  "tau_g_ns": 143.360000,
  "grain_bytes": 7168,
  "total_tokens": 131072,
  "max_egress_load": 94,
  "konig_us": 26.808320,
  "rtt_us": 1.200000,
  "barrier_us": 1.600000,
  "cct_us": 68.492493,
  "step_us": 92.319055,
  "gemv_us": 22.226562,
  "e2e_us": 90.719055,
  "throughput_GBs": 10176.924964,
  "latency_all": {
    "count": 131072,
    "mean_us": 16.958150,
    "p50_us": 16.886140,
    "p99_us": 27.857235,
    "min_us": 1.469937,
    "max_us": 34.542826
  },
  "latency_hot": {
    "count": 12004,
    "mean_us": 16.667377,
    "p50_us": 16.642344,
    "p99_us": 27.007837,
    "min_us": 1.749930,
    "max_us": 33.759066
  },
  "latency_cold": {
    "count": 65662,
    "mean_us": 17.036549,
    "p50_us": 16.959209,
    "p99_us": 28.108511,
    "min_us": 1.814580,
    "max_us": 33.949667
  },
  "dispatch_cct_us": 34.542826,
  "combine_cct_us": 33.949667,
  "roundtrip_step_us": 70.092493,
  "e2e_step_us": 92.319055
}
