{
  "scenario": 1,
  "scheme": "islip",
  "mode": "roundtrip",
  "batch": 128,
  "zipf_s": 0.000000,
  "topk": 8,
  "ep_size": 64,
  "seed": 38,
  "start_skew_us": 4.000000,
  "tau_g_ns": 143.360000,
  "grain_bytes": 7168,
  "total_tokens": 131072,
  "max_egress_load": 176,
  "konig_us": 47.882240,
  "rtt_us": 0.600000,
  "barrier_us": 0.800000,
  "cct_us": 58.987507,
  "step_us": 101.818757,
  "gemv_us": 42.031250,
  "e2e_us": 101.018757,
  "throughput_GBs": 9227.416637,
  "latency_all": {
    "count": 131072,
    "mean_us": 12.468580,
    "p50_us": 12.336833,
    "p99_us": 23.804681,
    "min_us": 1.282044,
    "max_us": 30.304266
  },
  "latency_hot": {
    "count": 12222,
    "mean_us": 12.303737,
    "p50_us": 12.205487,
    "p99_us": 23.569951,
    "min_us": 1.282044,
    "max_us": 27.034028
  },
  "latency_cold": {
    "count": 65392,
    "mean_us": 12.461308,
    "p50_us": 12.331838,
    "p99_us": 23.752294,
    "min_us": 1.304312,
    "max_us": 27.184688
  },
  "dispatch_cct_us": 28.683242,
  "combine_cct_us": 30.304266,
  "roundtrip_step_us": 59.787507,
  "e2e_step_us": 101.818757
}
