{
  "scenario": 1,
  "scheme": "ub_rg",
  "mode": "roundtrip",
  "batch": 128,
  "zipf_s": 0.300000,
  "topk": 8,
  "ep_size": 64,
  "seed": 51,
  "start_skew_us": 4.000000,
  "tau_g_ns": 143.360000,
  "grain_bytes": 7168,
  "total_tokens": 131072,
  "max_egress_load": 314,
  "konig_us": 87.306240,
  "rtt_us": 0.600000,
  "barrier_us": 0.800000,
  "cct_us": 114.789958,
  "step_us": 207.660270,
  "gemv_us": 92.070312,
  "e2e_us": 206.860270,
  "throughput_GBs": 4524.332434,
  "latency_all": {
    "count": 131072,
    "mean_us": 20.910739,
    "p50_us": 20.081827,
    "p99_us": 44.820273,
    "min_us": 1.153153,
    "max_us": 60.976762
  },
  "latency_hot": {
    "count": 21550,
    "mean_us": 26.915319,
    "p50_us": 26.450723,
    "p99_us": 50.429155,
    "min_us": 1.153153,
    "max_us": 60.976762
  },
  "latency_cold": {
    "count": 52752,
    "mean_us": 18.098054,
    "p50_us": 17.956844,
    "p99_us": 33.057110,
    "min_us": 1.177687,
    "max_us": 39.959410
  },
  "dispatch_cct_us": 60.976762,
  "combine_cct_us": 53.813196,
  "roundtrip_step_us": 115.589958,
  "e2e_step_us": 207.660270
}
