{
  "scenario": 4,
  "scheme": "packet_spray",
  "mode": "roundtrip",
  "batch": 128,
  "zipf_s": 0.000000,
  "topk": 8,
  "ep_size": 256,
  "seed": 43,
  "start_skew_us": 4.000000,
  "tau_g_ns": 143.360000,
  "grain_bytes": 7168,
  "total_tokens": 524288,
  "max_egress_load": 173,
  "konig_us": 48.168960,
  "rtt_us": 0.000000,
  "barrier_us": 6.000000,
  "cct_us": 88.434330,
  "step_us": 137.676517,
  "gemv_us": 43.242188,
  "e2e_us": 131.676517,
  "throughput_GBs": 27296.567799,
  "latency_all": {
    "count": 524288,
    "mean_us": 24.907139,
    "p50_us": 26.259015,
    "p99_us": 36.230926,
    "min_us": 0.424257,
    "max_us": 44.461964
  },
  "latency_hot": {
    "count": 51068,
    "mean_us": 20.762770,
    "p50_us": 20.722124,
    "p99_us": 38.511855,
    "min_us": 0.470263,
    "max_us": 43.672815
  },
  "latency_cold": {
    "count": 261698,
    "mean_us": 27.176358,
    "p50_us": 26.878170,
    "p99_us": 38.867756,
    "min_us": 0.424257,
    "max_us": 44.461964
  },
  "dispatch_cct_us": 43.972366,
  "combine_cct_us": 44.461964,
  "roundtrip_step_us": 94.434330,
  "e2e_step_us": 137.676517
}
