{
  "scenario": 4,
  "scheme": "ub_rg_pop",
  "mode": "roundtrip",
  "batch": 512,
  "zipf_s": 0.700000,
  "topk": 8,
  "ep_size": 512,
  "seed": 58,
  "start_skew_us": 4.000000,
  "tau_g_ns": 143.360000,
  "grain_bytes": 7168,
  "total_tokens": 4194304,
  "max_egress_load": 12976,
  "konig_us": 3551.744000,
  "rtt_us": 1.200000,
  "barrier_us": 1.600000,
  "cct_us": 3727.924625,
  "step_us": 7416.712125,
  "gemv_us": 3687.187500,
  "e2e_us": 7415.112125,
  "throughput_GBs": 4053.652153,
  "latency_all": {
    "count": 4194304,
    "mean_us": 138.895305,
    "p50_us": 21.867611,
    "p99_us": 1106.177545,
    "min_us": 1.503640,
    "max_us": 1865.082517
  },
  "latency_hot": {
    "count": 1740776,
    "mean_us": 284.264085,
    "p50_us": 52.247318,
    "p99_us": 1106.394708,
    "min_us": 1.514493,
    "max_us": 1865.082517
  },
  "latency_cold": {
    "count": 927608,
    "mean_us": 22.855053,
    "p50_us": 15.491036,
    "p99_us": 40.345975,
    "min_us": 1.518109,
    "max_us": 98.275579
  },
  "dispatch_cct_us": 1865.082517,
  "combine_cct_us": 1862.842108,
  "roundtrip_step_us": 3729.524625,
  "e2e_step_us": 7416.712125
}
