{
  "scenario": 1,
  "scheme": "ub_rg",
  "mode": "roundtrip",
  "batch": 128,
  "zipf_s": 0.900000,
  "topk": 8,
  "ep_size": 32,
  "seed": 59,
  "start_skew_us": 4.000000,
  "tau_g_ns": 143.360000,
  "grain_bytes": 7168,
  "total_tokens": 65536,
  "max_egress_load": 467,
  "konig_us": 133.038080,
  "rtt_us": 0.600000,
  "barrier_us": 0.800000,
  "cct_us": 164.489479,
  "step_us": 309.273854,
  "gemv_us": 143.984375,
  "e2e_us": 308.473854,
  "throughput_GBs": 1518.919372,
  "latency_all": {
    "count": 65536,
    "mean_us": 24.325046,
    "p50_us": 20.572296,
    "p99_us": 69.722354,
    "min_us": 1.305475,
    "max_us": 89.044973
  },
  "latency_hot": {
    "count": 18040,
    "mean_us": 36.375186,
    "p50_us": 35.545549,
    "p99_us": 74.402428,
    "min_us": 1.305475,
    "max_us": 89.044973
  },
  "latency_cold": {
    "count": 16780,
    "mean_us": 15.367422,
    "p50_us": 15.231011,
    "p99_us": 28.474574,
    "min_us": 1.593770,
    "max_us": 35.932115
  },
  "dispatch_cct_us": 89.044973,
  "combine_cct_us": 75.444506,
  "roundtrip_step_us": 165.289479,
  "e2e_step_us": 309.273854
}
