{
  "scenario": 1,
  "scheme": "ub_rg_pop",
  "mode": "roundtrip",
  "batch": 16,
  "zipf_s": 0.700000,
  "topk": 8,
  "ep_size": 128,
  "seed": 78,
  "start_skew_us": 4.000000,
  "tau_g_ns": 143.360000,
  "grain_bytes": 7168,
  "total_tokens": 32768,
  "max_egress_load": 142,
  "konig_us": 39.710720,
  "rtt_us": 0.900000,
  "barrier_us": 0.800000,
  "cct_us": 47.143068,
  "step_us": 89.935256,
  "gemv_us": 41.992188,
  "e2e_us": 89.135256,
  "throughput_GBs": 2611.667940,
  "latency_all": {
    "count": 32768,
    "mean_us": 6.258884,
    "p50_us": 5.487574,
    "p99_us": 19.057386,
    "min_us": 1.495179,
    "max_us": 24.848918
  },
  "latency_hot": {
    "count": 11256,
    "mean_us": 8.906216,
    "p50_us": 8.121938,
    "p99_us": 21.134232,
    "min_us": 1.925750,
    "max_us": 24.848918
  },
  "latency_cold": {
    "count": 8224,
    "mean_us": 4.389655,
    "p50_us": 4.437926,
    "p99_us": 6.864590,
    "min_us": 1.495179,
    "max_us": 7.674501
  },
  "dispatch_cct_us": 24.848918,
  "combine_cct_us": 22.294150,
  "roundtrip_step_us": 47.943068,
  "e2e_step_us": 89.935256
}
