{
  "scenario": 4,
  "scheme": "packet_spray",
  "mode": "roundtrip",
  "batch": 64,
  "zipf_s": 0.000000,
  "topk": 8,
  "ep_size": 256,
  "seed": 12,
  "start_skew_us": 4.000000,
  "tau_g_ns": 143.360000,
  "grain_bytes": 7168,
  "total_tokens": 262144,
  "max_egress_load": 99,
  "konig_us": 26.808320,
  "rtt_us": 0.000000,
  "barrier_us": 6.000000,
  "cct_us": 86.578052,
  "step_us": 114.960864,
  "gemv_us": 22.382812,
  "e2e_us": 108.960864,
  "throughput_GBs": 16345.111947,
  "latency_all": {
    "count": 262144,
    "mean_us": 29.562704,
    "p50_us": 29.022126,
    "p99_us": 37.562916,
    "min_us": 1.699347,
    "max_us": 44.145378
  },
  "latency_hot": {
    "count": 25828,
    "mean_us": 26.359348,
    "p50_us": 26.552066,
    "p99_us": 37.193646,
    "min_us": 3.835754,
    "max_us": 42.432673
  },
  "latency_cold": {
    "count": 130836,
    "mean_us": 31.014554,
    "p50_us": 31.400868,
    "p99_us": 40.704738,
    "min_us": 1.699347,
    "max_us": 44.145378
  },
  "dispatch_cct_us": 42.432673,
  "combine_cct_us": 44.145378,
  "roundtrip_step_us": 92.578052,
  "e2e_step_us": 114.960864
}
