{
  "scenario": 4,
  "scheme": "ub_rg_pop",
  "mode": "roundtrip",
  "batch": 16,
  "zipf_s": 0.700000,
  "topk": 8,
  "ep_size": 256,
  "seed": 75,
  "start_skew_us": 4.000000,
  "tau_g_ns": 143.360000,
  "grain_bytes": 7168,
  "total_tokens": 65536,
  "max_egress_load": 247,
  "konig_us": 68.239360,
  "rtt_us": 1.200000,
  "barrier_us": 1.600000,
  "cct_us": 77.881051,
  "step_us": 151.004489,
  "gemv_us": 71.523438,
  "e2e_us": 149.404489,
  "throughput_GBs": 3110.914466,
  "latency_all": {
    "count": 65536,
    "mean_us": 7.419955,
    "p50_us": 5.935313,
    "p99_us": 29.889020,
    "min_us": 1.448187,
    "max_us": 40.380206
  },
  "latency_hot": {
    "count": 25338,
    "mean_us": 11.017592,
    "p50_us": 9.124692,
    "p99_us": 33.827782,
    "min_us": 1.810366,
    "max_us": 40.380206
  },
  "latency_cold": {
    "count": 14972,
    "mean_us": 4.574189,
    "p50_us": 4.602449,
    "p99_us": 7.082771,
    "min_us": 1.448187,
    "max_us": 9.781443
  },
  "dispatch_cct_us": 40.380206,
  "combine_cct_us": 37.500846,
  "roundtrip_step_us": 79.481051,
  "e2e_step_us": 151.004489
}
