{
  "scenario": 1,
  "scheme": "ub_rg_pop",
  "mode": "roundtrip",
  "batch": 16,
  "zipf_s": 0.300000,
  "topk": 8,
  "ep_size": 64,
  "seed": 85,
  "start_skew_us": 4.000000,
  "tau_g_ns": 143.360000,
  "grain_bytes": 7168,
  "total_tokens": 16384,
  "max_egress_load": 48,
  "konig_us": 12.472320,
  "rtt_us": 0.900000,
  "barrier_us": 0.800000,
  "cct_us": 22.210310,
  "step_us": 34.924373,
  "gemv_us": 11.914062,
  "e2e_us": 34.124373,
  "throughput_GBs": 3362.709294,
  "latency_all": {
    "count": 16384,
    "mean_us": 5.012335,
    "p50_us": 4.968160,
    "p99_us": 8.766682,
    "min_us": 1.472240,
    "max_us": 11.890290
  },
  "latency_hot": {
    "count": 2700,
    "mean_us": 6.057367,
    "p50_us": 6.006982,
    "p99_us": 9.696660,
    "min_us": 1.605714,
    "max_us": 11.890290
  },
  "latency_cold": {
    "count": 6570,
    "mean_us": 4.566596,
    "p50_us": 4.465825,
    "p99_us": 7.596789,
    "min_us": 1.486106,
    "max_us": 8.547987
  },
  "dispatch_cct_us": 11.890290,
  "combine_cct_us": 10.320020,
  "roundtrip_step_us": 23.010310,
  "e2e_step_us": 34.924373
}
