{
  "scenario": 1,
  "scheme": "packet_spray",
  "mode": "roundtrip",
  "batch": 16,
  "zipf_s": 0.300000,
  "topk": 8,
  "ep_size": 64,
  "seed": 58,
  "start_skew_us": 4.000000,
  "tau_g_ns": 143.360000,
  "grain_bytes": 7168,
  "total_tokens": 16384,
  "max_egress_load": 45,
  "konig_us": 11.755520,
  "rtt_us": 0.000000,
  "barrier_us": 4.000000,
  "cct_us": 22.156841,
  "step_us": 37.680278,
  "gemv_us": 11.523438,
  "e2e_us": 33.680278,
  "throughput_GBs": 3116.763408,
  "latency_all": {
    "count": 16384,
    "mean_us": 5.976578,
    "p50_us": 6.065926,
    "p99_us": 9.122654,
    "min_us": 0.643961,
    "max_us": 11.987069
  },
  "latency_hot": {
    "count": 2638,
    "mean_us": 5.781654,
    "p50_us": 5.822589,
    "p99_us": 10.410109,
    "min_us": 0.733236,
    "max_us": 11.987069
  },
  "latency_cold": {
    "count": 6616,
    "mean_us": 6.151817,
    "p50_us": 6.192912,
    "p99_us": 8.979294,
    "min_us": 0.643961,
    "max_us": 10.169772
  },
  "dispatch_cct_us": 11.987069,
  "combine_cct_us": 10.169772,
  "roundtrip_step_us": 26.156841,
  "e2e_step_us": 37.680278
}
