{
  "scenario": 1,
  "scheme": "packet_spray",
  "mode": "roundtrip",
  "batch": 16,
  "zipf_s": 0.900000,
  "topk": 8,
  "ep_size": 128,
  "seed": 68,
  "start_skew_us": 4.000000,
  "tau_g_ns": 143.360000,
  "grain_bytes": 7168,
  "total_tokens": 32768,
  "max_egress_load": 215,
  "konig_us": 58.490880,
  "rtt_us": 0.000000,
  "barrier_us": 4.000000,
  "cct_us": 67.962996,
  "step_us": 132.080183,
  "gemv_us": 60.117188,
  "e2e_us": 128.080183,
  "throughput_GBs": 1778.321455,
  "latency_all": {
    "count": 32768,
    "mean_us": 12.855185,
    "p50_us": 9.900869,
    "p99_us": 31.088271,
    "min_us": 0.558610,
    "max_us": 34.661076
  },
  "latency_hot": {
    "count": 14474,
    "mean_us": 14.195423,
    "p50_us": 12.300143,
    "p99_us": 30.578080,
    "min_us": 1.170450,
    "max_us": 34.661076
  },
  "latency_cold": {
    "count": 6000,
    "mean_us": 11.609421,
    "p50_us": 6.498039,
    "p99_us": 31.581600,
    "min_us": 0.558610,
    "max_us": 33.301920
  },
  "dispatch_cct_us": 34.661076,
  "combine_cct_us": 33.301920,
  "roundtrip_step_us": 71.962996,
  "e2e_step_us": 132.080183
}
