{
  "scenario": 4,
  "scheme": "packet_spray",
  "mode": "roundtrip",
  "batch": 512,
  "zipf_s": 0.300000,
  "topk": 8,
  "ep_size": 256,
  "seed": 65,
  "start_skew_us": 4.000000,
  "tau_g_ns": 143.360000,
  "grain_bytes": 7168,
  "total_tokens": 2097152,
  "max_egress_load": 2115,
  "konig_us": 569.569280,
  "rtt_us": 0.000000,
  "barrier_us": 6.000000,
  "cct_us": 743.558099,
  "step_us": 1329.948724,
  "gemv_us": 580.390625,
  "e2e_us": 1323.948724,
  "throughput_GBs": 11302.981288,
  "latency_all": {
    "count": 2097152,
    "mean_us": 149.973235,
    "p50_us": 89.694910,
    "p99_us": 197.278369,
    "min_us": 1.199185,
    "max_us": 380.283128
  },
  "latency_hot": {
    "count": 388988,
    "mean_us": 151.973507,
    "p50_us": 145.820370,
    "p99_us": 306.877010,
    "min_us": 1.761318,
    "max_us": 363.274971
  },
  "latency_cold": {
    "count": 819700,
    "mean_us": 154.253153,
    "p50_us": 94.990930,
    "p99_us": 132.917566,
    "min_us": 1.789121,
    "max_us": 380.283128
  },
  "dispatch_cct_us": 363.274971,
  "combine_cct_us": 380.283128,
  "roundtrip_step_us": 749.558099,
  "e2e_step_us": 1329.948724
}
