{
  "scenario": 1,
  "scheme": "ub_rg",
  "mode": "roundtrip",
  "batch": 64,
  "zipf_s": 0.700000,
  "topk": 8,
  "ep_size": 128,
  "seed": 36,
  "start_skew_us": 4.000000,
  "tau_g_ns": 143.360000,
  "grain_bytes": 7168,
  "total_tokens": 131072,
  "max_egress_load": 576,
  "konig_us": 161.423360,
  "rtt_us": 0.600000,
  "barrier_us": 0.800000,
  "cct_us": 201.501841,
  "step_us": 374.137778,
  "gemv_us": 171.835938,
  "e2e_us": 373.337778,
  "throughput_GBs": 2511.171420,
  "latency_all": {
    "count": 131072,
    "mean_us": 21.534265,
    "p50_us": 17.305687,
    "p99_us": 80.698848,
    "min_us": 1.150033,
    "max_us": 103.267528
  },
  "latency_hot": {
    "count": 45300,
    "mean_us": 33.452909,
    "p50_us": 29.366911,
    "p99_us": 89.131910,
    "min_us": 1.350602,
    "max_us": 103.267528
  },
  "latency_cold": {
    "count": 32472,
    "mean_us": 13.333069,
    "p50_us": 13.360181,
    "p99_us": 24.573328,
    "min_us": 1.218482,
    "max_us": 29.272159
  },
  "dispatch_cct_us": 103.267528,
  "combine_cct_us": 98.234313,
  "roundtrip_step_us": 202.301841,
  "e2e_step_us": 374.137778
}
