{
  "scenario": 4,
  "scheme": "ub_rg_pop",
  "mode": "roundtrip",
  "batch": 512,
  "zipf_s": 0.300000,
  "topk": 8,
  "ep_size": 512,
  "seed": 34,
  "start_skew_us": 4.000000,
  "tau_g_ns": 143.360000,
  "grain_bytes": 7168,
  "total_tokens": 4194304,
  "max_egress_load": 2495,
  "konig_us": 686.694400,
  "rtt_us": 1.200000,
  "barrier_us": 1.600000,
  "cct_us": 723.279128,
  "step_us": 1441.949441,
  "gemv_us": 717.070312,
  "e2e_us": 1440.349441,
  "throughput_GBs": 20850.086851,
  "latency_all": {
    "count": 4194304,
    "mean_us": 49.003778,
    "p50_us": 21.974704,
    "p99_us": 160.931498,
    "min_us": 1.457628,
    "max_us": 362.160318
  },
  "latency_hot": {
    "count": 809376,
    "mean_us": 84.236022,
    "p50_us": 45.415139,
    "p99_us": 160.918244,
    "min_us": 1.686545,
    "max_us": 362.160318
  },
  "latency_cold": {
    "count": 1629478,
    "mean_us": 35.079813,
    "p50_us": 16.614319,
    "p99_us": 65.024224,
    "min_us": 1.457628,
    "max_us": 129.687206
  },
  "dispatch_cct_us": 361.118810,
  "combine_cct_us": 362.160318,
  "roundtrip_step_us": 724.879128,
  "e2e_step_us": 1441.949441
}
