{
  "scenario": 1,
  "scheme": "packet_spray",
  "mode": "roundtrip",
  "batch": 64,
  "zipf_s": 0.700000,
  "topk": 8,
  "ep_size": 32,
  "seed": 55,
  "start_skew_us": 4.000000,
  "tau_g_ns": 143.360000,
  "grain_bytes": 7168,
  "total_tokens": 32768,
  "max_egress_load": 215,
  "konig_us": 59.924480,
  "rtt_us": 0.000000,
  "barrier_us": 4.000000,
  "cct_us": 111.498844,
  "step_us": 178.741032,
  "gemv_us": 63.242188,
  "e2e_us": 174.741032,
  "throughput_GBs": 1314.085647,
  "latency_all": {
    "count": 32768,
    "mean_us": 32.889207,
    "p50_us": 30.984177,
    "p99_us": 52.631537,
    "min_us": 6.985004,
    "max_us": 56.000107
  },
  "latency_hot": {
    "count": 7906,
    "mean_us": 34.389338,
    "p50_us": 34.352747,
    "p99_us": 51.269227,
    "min_us": 11.572524,
    "max_us": 56.000107
  },
  "latency_cold": {
    "count": 10144,
    "mean_us": 32.771103,
    "p50_us": 29.621867,
    "p99_us": 53.778417,
    "min_us": 6.985004,
    "max_us": 55.498737
  },
  "dispatch_cct_us": 56.000107,
  "combine_cct_us": 55.498737,
  "roundtrip_step_us": 115.498844,
  "e2e_step_us": 178.741032
}
