{
  "scenario": 4,
  "scheme": "packet_spray",
  "mode": "roundtrip",
  "batch": 128,
  "zipf_s": 0.300000,
  "topk": 8,
  "ep_size": 512,
  "seed": 4,
  "start_skew_us": 4.000000,
  "tau_g_ns": 143.360000,
  "grain_bytes": 7168,
  "total_tokens": 1048576,
  "max_egress_load": 667,
  "konig_us": 178.196480,
  "rtt_us": 0.000000,
  "barrier_us": 6.000000,
  "cct_us": 242.007136,
  "step_us": 427.929011,
  "gemv_us": 179.921875,
  "e2e_us": 421.929011,
  "throughput_GBs": 17564.111289,
  "latency_all": {
    "count": 1048576,
    "mean_us": 50.151935,
    "p50_us": 39.816961,
    "p99_us": 62.565046,
    "min_us": 0.623440,
    "max_us": 127.964996
  },
  "latency_hot": {
    "count": 201374,
    "mean_us": 51.175971,
    "p50_us": 50.980676,
    "p99_us": 94.783804,
    "min_us": 1.877979,
    "max_us": 127.964996
  },
  "latency_cold": {
    "count": 408300,
    "mean_us": 51.017682,
    "p50_us": 42.814643,
    "p99_us": 54.808315,
    "min_us": 0.623440,
    "max_us": 114.042139
  },
  "dispatch_cct_us": 127.964996,
  "combine_cct_us": 114.042139,
  "roundtrip_step_us": 248.007136,
  "e2e_step_us": 427.929011
}
