{
  "scenario": 4,
  "scheme": "ub_rg",
  "mode": "roundtrip",
  "batch": 16,
  "zipf_s": 0.000000,
  "topk": 8,
  "ep_size": 256,
  "seed": 95,
  "start_skew_us": 4.000000,
  "tau_g_ns": 143.360000,
  "grain_bytes": 7168,
  "total_tokens": 65536,
  "max_egress_load": 31,
  "konig_us": 8.888320,
  "rtt_us": 0.800000,
  "barrier_us": 1.600000,
  "cct_us": 19.249316,
  "step_us": 27.568066,
  "gemv_us": 6.718750,
  "e2e_us": 25.968066,
  "throughput_GBs": 17040.080074,
  "latency_all": {
    "count": 65536,
    "mean_us": 4.974520,
    "p50_us": 4.996877,
    "p99_us": 8.109070,
    "min_us": 1.084676,
    "max_us": 9.679685
  },
  "latency_hot": {
    "count": 6496,
    "mean_us": 4.741213,
    "p50_us": 4.684051,
    "p99_us": 8.126179,
    "min_us": 1.389032,
    "max_us": 9.017306
  },
  "latency_cold": {
    "count": 33064,
    "mean_us": 4.996520,
    "p50_us": 5.012706,
    "p99_us": 8.150348,
    "min_us": 1.120786,
    "max_us": 9.455642
  },
  "dispatch_cct_us": 9.679685,
  "combine_cct_us": 9.569631,
  "roundtrip_step_us": 20.849316,
  "e2e_step_us": 27.568066
}
