{
  "scenario": 4,
  "scheme": "ub_rg_pop",
  "mode": "roundtrip",
  "batch": 16,
  "zipf_s": 0.700000,
  "topk": 8,
  "ep_size": 512,
  "seed": 86,
  "start_skew_us": 4.000000,
  "tau_g_ns": 143.360000,
  "grain_bytes": 7168,
  "total_tokens": 131072,
  "max_egress_load": 379,
  "konig_us": 106.373120,
  "rtt_us": 1.200000,
  "barrier_us": 1.600000,
  "cct_us": 115.952791,
  "step_us": 230.951229,
  "gemv_us": 113.398438,
  "e2e_us": 229.351229,
  "throughput_GBs": 4068.062772,
  "latency_all": {
    "count": 131072,
    "mean_us": 8.232734,
    "p50_us": 5.976112,
    "p99_us": 43.828530,
    "min_us": 1.591287,
    "max_us": 58.377409
  },
  "latency_hot": {
    "count": 54328,
    "mean_us": 12.810342,
    "p50_us": 9.621064,
    "p99_us": 50.799098,
    "min_us": 1.634749,
    "max_us": 58.377409
  },
  "latency_cold": {
    "count": 28970,
    "mean_us": 4.460487,
    "p50_us": 4.431734,
    "p99_us": 7.089482,
    "min_us": 1.604115,
    "max_us": 9.902739
  },
  "dispatch_cct_us": 58.377409,
  "combine_cct_us": 57.575383,
  "roundtrip_step_us": 117.552791,
  "e2e_step_us": 230.951229
}
