{
  "scenario": 1,
  "scheme": "packet_spray",
  "mode": "roundtrip",
  "batch": 64,
  "zipf_s": 0.700000,
  "topk": 8,
  "ep_size": 128,
  "seed": 20,
  "tau_g_ns": 143.360000,
  "grain_bytes": 7168,
  "total_tokens": 131072,
  "max_egress_load": 569,
  "konig_us": 158.699520,
  "rtt_us": 0.000000,
  "barrier_us": 4.000000,
  "cct_us": 176.546080,
  "step_us": 180.546080,
  "throughput_GBs": 5203.791165,
  "latency_all": {
    "count": 131072,
    "mean_us": 30.607776,
    "p50_us": 21.610640,
    "p99_us": 81.678480,
    "min_us": 0.536720,
    "max_us": 89.419920
  },
  "latency_hot": {
    "count": 45134,
    "mean_us": 34.624624,
    "p50_us": 30.068880,
    "p99_us": 78.811280,
    "min_us": 0.536720,
    "max_us": 89.419920
  },
  "latency_cold": {
    "count": 32326,
    "mean_us": 28.442623,
    "p50_us": 13.152400,
    "p99_us": 83.828880,
    "min_us": 0.536720,
    "max_us": 87.126160
  },
  "dispatch_cct_us": 89.419920,
  "combine_cct_us": 87.126160,
  "roundtrip_step_us": 180.546080
}
