{
  "scenario": 1,
  "scheme": "packet_spray",
  "mode": "roundtrip",
  "batch": 16,
  "zipf_s": 0.300000,
  "topk": 8,
  "ep_size": 128,
  "seed": 52,
  "start_skew_us": 4.000000,
  "tau_g_ns": 143.360000,
  "grain_bytes": 7168,
  "total_tokens": 32768,
  "max_egress_load": 55,
  "konig_us": 14.766080,
  "rtt_us": 0.000000,
  "barrier_us": 4.000000,
  "cct_us": 53.469119,
  "step_us": 72.234744,
  "gemv_us": 14.765625,
  "e2e_us": 68.234744,
  "throughput_GBs": 3251.635030,
  "latency_all": {
    "count": 32768,
    "mean_us": 18.743279,
    "p50_us": 19.238735,
    "p99_us": 25.440837,
    "min_us": 0.536720,
    "max_us": 28.956236
  },
  "latency_hot": {
    "count": 5592,
    "mean_us": 18.068331,
    "p50_us": 18.022791,
    "p99_us": 26.805836,
    "min_us": 0.536720,
    "max_us": 28.956236
  },
  "latency_cold": {
    "count": 13258,
    "mean_us": 19.239003,
    "p50_us": 19.815352,
    "p99_us": 24.867397,
    "min_us": 5.625699,
    "max_us": 26.444357
  },
  "dispatch_cct_us": 28.956236,
  "combine_cct_us": 24.512883,
  "roundtrip_step_us": 57.469119,
  "e2e_step_us": 72.234744
}
