{
  "scenario": 4,
  "scheme": "ub_rg_pop",
  "mode": "roundtrip",
  "batch": 512,
  "zipf_s": 0.300000,
  "topk": 8,
  "ep_size": 256,
  "seed": 3,
  "start_skew_us": 4.000000,
  "tau_g_ns": 143.360000,
  "grain_bytes": 7168,
  "total_tokens": 2097152,
  "max_egress_load": 1975,
  "konig_us": 547.491840,
  "rtt_us": 1.200000,
  "barrier_us": 1.600000,
  "cct_us": 595.340389,
  "step_us": 1173.151326,
  "gemv_us": 576.210938,
  "e2e_us": 1171.551326,
  "throughput_GBs": 12813.679870,
  "latency_all": {
    "count": 2097152,
    "mean_us": 55.314491,
    "p50_us": 22.810470,
    "p99_us": 130.531643,
    "min_us": 1.422439,
    "max_us": 299.481510
  },
  "latency_hot": {
    "count": 390018,
    "mean_us": 88.762362,
    "p50_us": 81.639782,
    "p99_us": 241.088107,
    "min_us": 2.734153,
    "max_us": 299.481510
  },
  "latency_cold": {
    "count": 820752,
    "mean_us": 42.220644,
    "p50_us": 28.373098,
    "p99_us": 67.466161,
    "min_us": 1.710169,
    "max_us": 102.563503
  },
  "dispatch_cct_us": 295.858879,
  "combine_cct_us": 299.481510,
  "roundtrip_step_us": 596.940389,
  "e2e_step_us": 1173.151326
}
