{
  "scenario": 1,
  "scheme": "packet_spray",
  "mode": "roundtrip",
  "batch": 256,
  "zipf_s": 0.300000,
  "topk": 8,
  "ep_size": 64,
  "seed": 95,
  "tau_g_ns": 143.360000,
  "grain_bytes": 7168,
  "total_tokens": 262144,
  "max_egress_load": 604,
  "konig_us": 169.738240,
  "rtt_us": 0.000000,
  "barrier_us": 4.000000,
  "cct_us": 240.771360,
  "step_us": 244.771360,
  "throughput_GBs": 7676.748587,
  "latency_all": {
    "count": 262144,
    "mean_us": 56.928603,
    "p50_us": 52.289680,
    "p99_us": 97.448080,
    "min_us": 0.536720,
    "max_us": 121.245840
  },
  "latency_hot": {
    "count": 42726,
    "mean_us": 55.519233,
    "p50_us": 56.447120,
    "p99_us": 109.203600,
    "min_us": 0.536720,
    "max_us": 121.245840
  },
  "latency_cold": {
    "count": 105872,
    "mean_us": 59.825490,
    "p50_us": 54.726800,
    "p99_us": 112.644240,
    "min_us": 0.536720,
    "max_us": 119.525520
  },
  "dispatch_cct_us": 121.245840,
  "combine_cct_us": 119.525520,
  "roundtrip_step_us": 244.771360
}
