{
  "scenario": 4,
  "scheme": "packet_spray",
  "mode": "roundtrip",
  "batch": 512,
  "zipf_s": 0.000000,
  "topk": 8,
  "ep_size": 128,
  "seed": 41,
  "start_skew_us": 4.000000,
  "tau_g_ns": 143.360000,
  "grain_bytes": 7168,
  "total_tokens": 1048576,
  "max_egress_load": 623,
  "konig_us": 172.892160,
  "rtt_us": 0.000000,
  "barrier_us": 6.000000,
  "cct_us": 338.939569,
  "step_us": 509.588006,
  "gemv_us": 164.648438,
  "e2e_us": 503.588006,
  "throughput_GBs": 14749.548016,
  "latency_all": {
    "count": 1048576,
    "mean_us": 100.196737,
    "p50_us": 94.462934,
    "p99_us": 147.436894,
    "min_us": 0.396248,
    "max_us": 171.447254
  },
  "latency_hot": {
    "count": 98214,
    "mean_us": 83.588420,
    "p50_us": 83.683245,
    "p99_us": 152.953814,
    "min_us": 1.483600,
    "max_us": 171.447254
  },
  "latency_cold": {
    "count": 525952,
    "mean_us": 109.160828,
    "p50_us": 107.296094,
    "p99_us": 143.890061,
    "min_us": 1.399768,
    "max_us": 168.654174
  },
  "dispatch_cct_us": 171.447254,
  "combine_cct_us": 167.492315,
  "roundtrip_step_us": 344.939569,
  "e2e_step_us": 509.588006
}
