{
  "scenario": 4,
  "scheme": "ub_rg_pop",
  "mode": "roundtrip",
  "batch": 64,
  "zipf_s": 0.700000,
  "topk": 8,
  "ep_size": 512,
  "seed": 81,
  "start_skew_us": 4.000000,
  "tau_g_ns": 143.360000,
  "grain_bytes": 7168,
  "total_tokens": 524288,
  "max_egress_load": 1621,
  "konig_us": 443.125760,
  "rtt_us": 1.200000,
  "barrier_us": 1.600000,
  "cct_us": 498.794555,
  "step_us": 959.496117,
  "gemv_us": 459.101562,
  "e2e_us": 957.896117,
  "throughput_GBs": 3916.739544,
  "latency_all": {
    "count": 524288,
    "mean_us": 31.835855,
    "p50_us": 23.348820,
    "p99_us": 52.034100,
    "min_us": 1.809836,
    "max_us": 254.702062
  },
  "latency_hot": {
    "count": 218692,
    "mean_us": 50.055317,
    "p50_us": 34.156076,
    "p99_us": 191.606265,
    "min_us": 1.904904,
    "max_us": 254.702062
  },
  "latency_cold": {
    "count": 116246,
    "mean_us": 16.908198,
    "p50_us": 16.931578,
    "p99_us": 29.104141,
    "min_us": 1.809836,
    "max_us": 40.886418
  },
  "dispatch_cct_us": 254.702062,
  "combine_cct_us": 244.092493,
  "roundtrip_step_us": 500.394555,
  "e2e_step_us": 959.496117
}
