{
  "scenario": 3,
  "scheme": "packet_spray",
  "mode": "roundtrip",
  "batch": 16,
  "zipf_s": 0.700000,
  "topk": 8,
  "ep_size": 256,
  "seed": 18,
  "tau_g_ns": 143.360000,
  "grain_bytes": 7168,
  "total_tokens": 65536,
  "max_egress_load": 258,
  "konig_us": 69.959680,
  "rtt_us": 0.000000,
  "barrier_us": 8.000000,
  "cct_us": 76.020640,
  "step_us": 84.020640,
  "throughput_GBs": 5591.031537,
  "latency_all": {
    "count": 65536,
    "mean_us": 13.044107,
    "p50_us": 9.194960,
    "p99_us": 35.429840,
    "min_us": 0.880080,
    "max_us": 39.443920
  },
  "latency_hot": {
    "count": 25052,
    "mean_us": 13.601918,
    "p50_us": 10.485200,
    "p99_us": 33.996240,
    "min_us": 0.880080,
    "max_us": 39.443920
  },
  "latency_cold": {
    "count": 15346,
    "mean_us": 12.819195,
    "p50_us": 5.324240,
    "p99_us": 35.716560,
    "min_us": 0.880080,
    "max_us": 36.576720
  },
  "dispatch_cct_us": 39.443920,
  "combine_cct_us": 36.576720,
  "roundtrip_step_us": 84.020640
}
