{
  "scenario": 1,
  "scheme": "islip",
  "mode": "roundtrip",
  "batch": 128,
  "zipf_s": 0.300000,
  "topk": 8,
  "ep_size": 64,
  "seed": 35,
  "start_skew_us": 4.000000,
  "tau_g_ns": 143.360000,
  "grain_bytes": 7168,
  "total_tokens": 131072,
  "max_egress_load": 310,
  "konig_us": 86.876160,
  "rtt_us": 0.600000,
  "barrier_us": 0.800000,
  "cct_us": 119.095314,
  "step_us": 212.160939,
  "gemv_us": 92.265625,
  "e2e_us": 211.360939,
  "throughput_GBs": 4428.355668,
  "latency_all": {
    "count": 131072,
    "mean_us": 21.658558,
    "p50_us": 20.785860,
    "p99_us": 46.489843,
    "min_us": 1.180738,
    "max_us": 62.267673
  },
  "latency_hot": {
    "count": 21504,
    "mean_us": 28.916795,
    "p50_us": 28.519496,
    "p99_us": 53.208450,
    "min_us": 1.363869,
    "max_us": 62.267673
  },
  "latency_cold": {
    "count": 52362,
    "mean_us": 18.642088,
    "p50_us": 18.568560,
    "p99_us": 32.965791,
    "min_us": 1.180738,
    "max_us": 39.928867
  },
  "dispatch_cct_us": 62.267673,
  "combine_cct_us": 56.827640,
  "roundtrip_step_us": 119.895314,
  "e2e_step_us": 212.160939
}
