{
  "scenario": 4,
  "scheme": "packet_spray",
  "mode": "roundtrip",
  "batch": 64,
  "zipf_s": 0.900000,
  "topk": 8,
  "ep_size": 128,
  "seed": 4,
  "start_skew_us": 4.000000,
  "tau_g_ns": 143.360000,
  "grain_bytes": 7168,
  "total_tokens": 131072,
  "max_egress_load": 823,
  "konig_us": 228.229120,
  "rtt_us": 0.000000,
  "barrier_us": 6.000000,
  "cct_us": 271.919547,
  "step_us": 518.075797,
  "gemv_us": 240.156250,
  "e2e_us": 512.075797,
  "throughput_GBs": 1813.487721,
  "latency_all": {
    "count": 131072,
    "mean_us": 49.634617,
    "p50_us": 39.019441,
    "p99_us": 119.668880,
    "min_us": 0.193360,
    "max_us": 141.928747
  },
  "latency_hot": {
    "count": 57790,
    "mean_us": 55.719898,
    "p50_us": 50.058161,
    "p99_us": 123.722027,
    "min_us": 0.193360,
    "max_us": 141.928747
  },
  "latency_cold": {
    "count": 23882,
    "mean_us": 44.191396,
    "p50_us": 28.363732,
    "p99_us": 116.514960,
    "min_us": 2.533847,
    "max_us": 129.990800
  },
  "dispatch_cct_us": 141.928747,
  "combine_cct_us": 129.990800,
  "roundtrip_step_us": 277.919547,
  "e2e_step_us": 518.075797
}
