{
  "scenario": 1,
  "scheme": "ub_rg",
  "mode": "roundtrip",
  "batch": 16,
  "zipf_s": 0.300000,
  "topk": 8,
  "ep_size": 128,
  "seed": 94,
  "start_skew_us": 4.000000,
  "tau_g_ns": 143.360000,
  "grain_bytes": 7168,
  "total_tokens": 32768,
  "max_egress_load": 56,
  "konig_us": 15.196160,
  "rtt_us": 0.600000,
  "barrier_us": 0.800000,
  "cct_us": 54.762696,
  "step_us": 70.914258,
  "gemv_us": 15.351562,
  "e2e_us": 70.114258,
  "throughput_GBs": 3312.183320,
  "latency_all": {
    "count": 32768,
    "mean_us": 14.397609,
    "p50_us": 14.494312,
    "p99_us": 23.419423,
    "min_us": 1.151520,
    "max_us": 29.072823
  },
  "latency_hot": {
    "count": 5754,
    "mean_us": 15.613029,
    "p50_us": 15.976619,
    "p99_us": 24.435847,
    "min_us": 1.151520,
    "max_us": 29.072823
  },
  "latency_cold": {
    "count": 12954,
    "mean_us": 14.044310,
    "p50_us": 13.922691,
    "p99_us": 22.762547,
    "min_us": 1.815009,
    "max_us": 26.557713
  },
  "dispatch_cct_us": 29.072823,
  "combine_cct_us": 25.689873,
  "roundtrip_step_us": 55.562696,
  "e2e_step_us": 70.914258
}
