{
  "scenario": 4,
  "scheme": "ub_rg_pop",
  "mode": "roundtrip",
  "batch": 512,
  "zipf_s": 0.900000,
  "topk": 8,
  "ep_size": 128,
  "seed": 49,
  "start_skew_us": 4.000000,
  "tau_g_ns": 143.360000,
  "grain_bytes": 7168,
  "total_tokens": 1048576,
  "max_egress_load": 6439,
  "konig_us": 1800.028160,
  "rtt_us": 1.200000,
  "barrier_us": 1.600000,
  "cct_us": 1873.651600,
  "step_us": 3786.618788,
  "gemv_us": 1911.367188,
  "e2e_us": 3785.018788,
  "throughput_GBs": 1984.935160,
  "latency_all": {
    "count": 1048576,
    "mean_us": 133.896578,
    "p50_us": 27.884927,
    "p99_us": 463.276296,
    "min_us": 1.575111,
    "max_us": 936.914681
  },
  "latency_hot": {
    "count": 463016,
    "mean_us": 246.689963,
    "p50_us": 163.730109,
    "p99_us": 478.356593,
    "min_us": 2.877456,
    "max_us": 936.914681
  },
  "latency_cold": {
    "count": 190280,
    "mean_us": 26.144465,
    "p50_us": 25.597053,
    "p99_us": 49.330058,
    "min_us": 1.575111,
    "max_us": 64.613572
  },
  "dispatch_cct_us": 936.736920,
  "combine_cct_us": 936.914681,
  "roundtrip_step_us": 1875.251600,
  "e2e_step_us": 3786.618788
}
