{
  "scenario": 4,
  "scheme": "packet_spray",
  "mode": "roundtrip",
  "batch": 256,
  "zipf_s": 0.300000,
  "topk": 8,
  "ep_size": 256,
  "seed": 37,
  "start_skew_us": 4.000000,
  "tau_g_ns": 143.360000,
  "grain_bytes": 7168,
  "total_tokens": 1048576,
  "max_egress_load": 1079,
  "konig_us": 287.150080,
  "rtt_us": 0.000000,
  "barrier_us": 6.000000,
  "cct_us": 368.411436,
  "step_us": 662.927061,
  "gemv_us": 288.515625,
  "e2e_us": 656.927061,
  "throughput_GBs": 11337.887996,
  "latency_all": {
    "count": 1048576,
    "mean_us": 71.257207,
    "p50_us": 44.476637,
    "p99_us": 83.950628,
    "min_us": 0.357833,
    "max_us": 184.914555
  },
  "latency_hot": {
    "count": 195048,
    "mean_us": 72.339070,
    "p50_us": 70.963381,
    "p99_us": 145.490555,
    "min_us": 0.929920,
    "max_us": 183.496881
  },
  "latency_cold": {
    "count": 408868,
    "mean_us": 73.402437,
    "p50_us": 50.414856,
    "p99_us": 68.615802,
    "min_us": 0.412301,
    "max_us": 184.914555
  },
  "dispatch_cct_us": 183.496881,
  "combine_cct_us": 184.914555,
  "roundtrip_step_us": 374.411436,
  "e2e_step_us": 662.927061
}
