{
  "scenario": 4,
  "scheme": "packet_spray",
  "mode": "roundtrip",
  "batch": 512,
  "zipf_s": 0.000000,
  "topk": 8,
  "ep_size": 512,
  "seed": 68,
  "start_skew_us": 4.000000,
  "tau_g_ns": 143.360000,
  "grain_bytes": 7168,
  "total_tokens": 4194304,
  "max_egress_load": 630,
  "konig_us": 176.189440,
  "rtt_us": 0.000000,
  "barrier_us": 6.000000,
  "cct_us": 358.680173,
  "step_us": 530.773923,
  "gemv_us": 166.093750,
  "e2e_us": 524.773923,
  "throughput_GBs": 56643.270872,
  "latency_all": {
    "count": 4194304,
    "mean_us": 104.922024,
    "p50_us": 99.364332,
    "p99_us": 160.679100,
    "min_us": 0.754324,
    "max_us": 184.514568
  },
  "latency_hot": {
    "count": 417924,
    "mean_us": 88.686121,
    "p50_us": 119.308439,
    "p99_us": 159.881675,
    "min_us": 3.634000,
    "max_us": 179.889340
  },
  "latency_cold": {
    "count": 2096662,
    "mean_us": 113.851447,
    "p50_us": 94.197768,
    "p99_us": 157.568492,
    "min_us": 1.229133,
    "max_us": 184.514568
  },
  "dispatch_cct_us": 184.514568,
  "combine_cct_us": 174.165605,
  "roundtrip_step_us": 364.680173,
  "e2e_step_us": 530.773923
}
