{
  "scenario": 1,
  "scheme": "packet_spray",
  "mode": "roundtrip",
  "batch": 16,
  "zipf_s": 0.900000,
  "topk": 8,
  "ep_size": 32,
  "seed": 77,
  "start_skew_us": 4.000000,
  "tau_g_ns": 143.360000,
  "grain_bytes": 7168,
  "total_tokens": 8192,
  "max_egress_load": 65,
  "konig_us": 17.633280,
  "rtt_us": 0.000000,
  "barrier_us": 4.000000,
  "cct_us": 42.307262,
  "step_us": 64.315074,
  "gemv_us": 18.007812,
  "e2e_us": 60.315074,
  "throughput_GBs": 913.009222,
  "latency_all": {
    "count": 8192,
    "mean_us": 13.613451,
    "p50_us": 14.247647,
    "p99_us": 20.195748,
    "min_us": 0.536720,
    "max_us": 21.415647
  },
  "latency_hot": {
    "count": 2270,
    "mean_us": 13.135600,
    "p50_us": 13.387487,
    "p99_us": 20.625828,
    "min_us": 0.966800,
    "max_us": 21.415647
  },
  "latency_cold": {
    "count": 2160,
    "mean_us": 14.581771,
    "p50_us": 15.464868,
    "p99_us": 20.318175,
    "min_us": 0.536720,
    "max_us": 20.891615
  },
  "dispatch_cct_us": 21.415647,
  "combine_cct_us": 20.891615,
  "roundtrip_step_us": 46.307262,
  "e2e_step_us": 64.315074
}
