{
  "scenario": 1,
  "scheme": "ub_rg",
  "mode": "roundtrip",
  "batch": 512,
  "zipf_s": 0.700000,
  "topk": 8,
  "ep_size": 32,
  "seed": 88,
  "start_skew_us": 4.000000,
  "tau_g_ns": 143.360000,
  "grain_bytes": 7168,
  "total_tokens": 262144,
  "max_egress_load": 1616,
  "konig_us": 461.332480,
  "rtt_us": 0.600000,
  "barrier_us": 0.800000,
  "cct_us": 484.559615,
  "step_us": 985.906490,
  "gemv_us": 500.546875,
  "e2e_us": 985.106490,
  "throughput_GBs": 1905.909141,
  "latency_all": {
    "count": 262144,
    "mean_us": 57.736824,
    "p50_us": 35.363009,
    "p99_us": 200.381877,
    "min_us": 1.213202,
    "max_us": 242.587892
  },
  "latency_hot": {
    "count": 62630,
    "mean_us": 105.303991,
    "p50_us": 102.426629,
    "p99_us": 232.673458,
    "min_us": 1.650017,
    "max_us": 242.587892
  },
  "latency_cold": {
    "count": 78906,
    "mean_us": 30.369386,
    "p50_us": 29.883487,
    "p99_us": 61.344825,
    "min_us": 1.580010,
    "max_us": 71.236268
  },
  "dispatch_cct_us": 242.587892,
  "combine_cct_us": 241.971724,
  "roundtrip_step_us": 485.359615,
  "e2e_step_us": 985.906490
}
