{
  "scenario": 4,
  "scheme": "packet_spray",
  "mode": "roundtrip",
  "batch": 64,
  "zipf_s": 0.900000,
  "topk": 8,
  "ep_size": 512,
  "seed": 33,
  "start_skew_us": 4.000000,
  "tau_g_ns": 143.360000,
  "grain_bytes": 7168,
  "total_tokens": 524288,
  "max_egress_load": 2734,
  "konig_us": 755.650560,
  "rtt_us": 0.000000,
  "barrier_us": 6.000000,
  "cct_us": 791.467836,
  "step_us": 1590.124086,
  "gemv_us": 792.656250,
  "e2e_us": 1584.124086,
  "throughput_GBs": 2363.398188,
  "latency_all": {
    "count": 524288,
    "mean_us": 115.161473,
    "p50_us": 17.189568,
    "p99_us": 252.732281,
    "min_us": 0.348582,
    "max_us": 412.581743
  },
  "latency_hot": {
    "count": 290776,
    "mean_us": 127.225277,
    "p50_us": 57.706846,
    "p99_us": 355.524463,
    "min_us": 0.348582,
    "max_us": 408.567663
  },
  "latency_cold": {
    "count": 76196,
    "mean_us": 99.716200,
    "p50_us": 15.117547,
    "p99_us": 364.842863,
    "min_us": 0.360481,
    "max_us": 412.581743
  },
  "dispatch_cct_us": 378.886093,
  "combine_cct_us": 412.581743,
  "roundtrip_step_us": 797.467836,
  "e2e_step_us": 1590.124086
}
