{
  "scenario": 4,
  "scheme": "ub_rg",
  "mode": "roundtrip",
  "batch": 256,
  "zipf_s": 0.700000,
  "topk": 8,
  "ep_size": 128,
  "seed": 23,
  "start_skew_us": 4.000000,
  "tau_g_ns": 143.360000,
  "grain_bytes": 7168,
  "total_tokens": 524288,
  "max_egress_load": 2308,
  "konig_us": 646.410240,
  "rtt_us": 0.800000,
  "barrier_us": 1.600000,
  "cct_us": 667.445421,
  "step_us": 1356.623546,
  "gemv_us": 687.578125,
  "e2e_us": 1355.023546,
  "throughput_GBs": 2770.183663,
  "latency_all": {
    "count": 524288,
    "mean_us": 43.998949,
    "p50_us": 19.096864,
    "p99_us": 90.136760,
    "min_us": 1.191760,
    "max_us": 333.985604
  },
  "latency_hot": {
    "count": 180514,
    "mean_us": 88.954403,
    "p50_us": 71.472171,
    "p99_us": 302.439671,
    "min_us": 1.820204,
    "max_us": 333.985604
  },
  "latency_cold": {
    "count": 129800,
    "mean_us": 13.411335,
    "p50_us": 13.124188,
    "p99_us": 26.671892,
    "min_us": 1.191760,
    "max_us": 38.177919
  },
  "dispatch_cct_us": 333.985604,
  "combine_cct_us": 333.459817,
  "roundtrip_step_us": 669.045421,
  "e2e_step_us": 1356.623546
}
