{
  "scenario": 1,
  "scheme": "packet_spray",
  "mode": "roundtrip",
  "batch": 512,
  "zipf_s": 0.000000,
  "topk": 8,
  "ep_size": 128,
  "seed": 86,
  "start_skew_us": 4.000000,
  "tau_g_ns": 143.360000,
  "grain_bytes": 7168,
  "total_tokens": 1048576,
  "max_egress_load": 583,
  "konig_us": 159.703040,
  "rtt_us": 0.000000,
  "barrier_us": 4.000000,
  "cct_us": 329.523711,
  "step_us": 499.383086,
  "gemv_us": 165.859375,
  "e2e_us": 495.383086,
  "throughput_GBs": 15050.955827,
  "latency_all": {
    "count": 1048576,
    "mean_us": 102.483170,
    "p50_us": 96.697663,
    "p99_us": 149.936581,
    "min_us": 9.992040,
    "max_us": 167.999941
  },
  "latency_hot": {
    "count": 97516,
    "mean_us": 84.871031,
    "p50_us": 85.054584,
    "p99_us": 154.509820,
    "min_us": 10.278760,
    "max_us": 167.999941
  },
  "latency_cold": {
    "count": 524848,
    "mean_us": 111.741360,
    "p50_us": 109.939141,
    "p99_us": 145.191420,
    "min_us": 9.992040,
    "max_us": 166.853061
  },
  "dispatch_cct_us": 167.999941,
  "combine_cct_us": 161.523770,
  "roundtrip_step_us": 333.523711,
  "e2e_step_us": 499.383086
}
